ofxcloudsync/__init__.py
ofxcloudsync/ofx_sync.py
ofxcloudsync/pca_ofx2cloud.py
ofxcs/__init__.py
orcaflex_cloudsync-0.2.5.dist-info/entry_points.txt
orcaflex_cloudsync-0.2.5.dist-info/WHEEL
orcaflex_cloudsync-0.2.5.dist-info/METADATA
orcaflex_cloudsync-0.2.5.dist-info/RECORD
